README.rst
setup.py
etcd_tree/__init__.py
etcd_tree/etcd.py
etcd_tree/node.py
etcd_tree/util.py
etcd_tree.egg-info/PKG-INFO
etcd_tree.egg-info/SOURCES.txt
etcd_tree.egg-info/dependency_links.txt
etcd_tree.egg-info/not-zip-safe
etcd_tree.egg-info/requires.txt
etcd_tree.egg-info/top_level.txt
scripts/etcd2yaml
scripts/etcdmon
scripts/yaml2etcd
viewer/etcd-tree