Metadata-Version: 1.1
Name: etcd-tree
Version: 0.9.19
Summary: Dynamic etcd state
Home-page: https://github.com/m-o-a-t/etcd-tree
Author: Matthias Urlichs
Author-email: matthias@urlichs.de
License: GPL
Download-URL: https://github.com/M-o-a-T/etcd-tree/archive/master.zip
Keywords: etcd asyncio
Platform: UNKNOWN
Classifier: Topic :: System :: Distributed Computing
Classifier: Topic :: Software Development :: Libraries
Classifier: License :: OSI Approved :: MIT License
Classifier: Programming Language :: Python :: 3
Classifier: Programming Language :: Python :: 3.5
Classifier: Topic :: Database :: Front-Ends
